svg_plot/__init__.py
svg_plot/svg_plot.py
svg_plot/svg_renderer.py
svg_plot/ticker_extended.py
svg_plot-0.1.1.dist-info/LICENSE
svg_plot-0.1.1.dist-info/METADATA
svg_plot-0.1.1.dist-info/WHEEL
svg_plot-0.1.1.dist-info/top_level.txt
svg_plot-0.1.1.dist-info/RECORD
