Metadata-Version: 2.1
Name: svg-plot
Version: 0.1.1
Summary: Lightweight tool to generate SVG plots.
Home-page: https://github.com/tgree/svg_plot
Author: Terry Greeniaus
Author-email: terrygreeniaus@gmail.com
License: License :: OSI Approved :: MIT License
Keywords: svg plot
Platform: UNKNOWN
Classifier: Operating System :: POSIX
Classifier: Programming Language :: Python :: 3
Classifier: License :: OSI Approved :: MIT License
Requires-Python: >=3.6
